carrier_sample/__init__.py
carrier_sample/carrier_sample.py
carrier_sample/result.py
carrier_sample-0.1.15.data/data/carrier_sample.exe
carrier_sample-0.1.15.dist-info/LICENSE
carrier_sample-0.1.15.dist-info/METADATA
carrier_sample-0.1.15.dist-info/WHEEL
carrier_sample-0.1.15.dist-info/top_level.txt
carrier_sample-0.1.15.dist-info/RECORD
