Metadata-Version: 2.1
Name: carrier-sample
Version: 0.1.15
Summary: high speed acquisition card program for carrier && single && highlight
Home-page: https://github.com/KD-Group/Carrier.Sample
Author: WingC
Author-email: 1018957763@qq.com
License: UNKNOWN
Keywords: carrier sample
Platform: UNKNOWN
Classifier: Programming Language :: Python :: 3
Classifier: License :: OSI Approved :: MIT License
Classifier: Operating System :: OS Independent
Requires-Dist: requests
Provides-Extra: test
Requires-Dist: pytest ; extra == 'test'
